{"title":"Combined feed","url":"https://factcheckr.github.io/careet/all.xml","elements":[{"title":"undefined (Careet ─ Contents ─ MZ 용어 사전)","contents":"‘느낌 좋은’의 줄임말. 힙하고 멋진 것을 가리키는 Z세대 신조어.","retrieved":1732000894835},{"title":"undefined (Careet ─ Contents ─ MZ 용어 사전)","contents":"‘새롭고 놀랍다’란 뜻으로 신기하면서도 참신한 경우에 사용되는 신조어.","retrieved":1732000894836},{"title":"undefined (Careet ─ Contents ─ MZ 용어 사전)","contents":"어린 시절부터 디지털 환경에서 성장한 세대를 뜻함.","retrieved":1732000894836},{"title":"undefined (Careet ─ Contents ─ MZ 용어 사전)","contents":"‘텍스트 대치’의 줄임말. 스마트폰 특정 자판을 누르면 정해진 문구가 나오도록 설정해둔 기능을 뜻함. Z세대는 보통 이모티콘이 들어간 주접 문구를 텍대로 설정해두고 활용함.","retrieved":1732000894837},{"title":"undefined (Careet ─ Contents ─ MZ 용어 사전)","contents":"‘버추얼 유튜버’의 줄임말. 모션 캡처 등을 활용해 표정과 움직임을 실시간으로 따라하는 아바타를 내세워 방송하는 유튜버.","retrieved":1732000894839},{"title":"undefined (Careet ─ Contents ─ MZ 용어 사전)","contents":"식사(meal)와 준비(preparation)의 합성어. 최대 일주일치 식사를 미리 준비해뒀다가 식사 때마다 먹는 방법.","retrieved":1732000894840}]}