{"title":"Combined feed","url":"https://factcheckr.github.io/careet/all.xml","elements":[{"title":"undefined (Careet ─ Contents ─ MZ 용어 사전)","contents":"음식에 대해 식견이 높거나, 맛있는 음식 조합을 잘 아는 사람들을 뜻하는 말","retrieved":1716438075521},{"title":"undefined (Careet ─ Contents ─ MZ 용어 사전)","contents":"‘Fear Of Missing Out’의 약자로 소외되거나 뒤처지는 것에 대한 두려움을 뜻함.","retrieved":1716438075522},{"title":"undefined (Careet ─ Contents ─ MZ 용어 사전)","contents":"‘순식간에 삭제되다’의 줄임말. ‘너무 재밌어서 시간 가는 줄 몰랐다’, ‘너무 맛있어서 순식간에 다 먹어 버렸다.’ 등의 맥락에서 사용됨.","retrieved":1716438075525},{"title":"undefined (Careet ─ Contents ─ MZ 용어 사전)","contents":"‘피 튀기는 경쟁률을 자랑하는 티케팅’의 줄임말.","retrieved":1716438075526},{"title":"undefined (Careet ─ Contents ─ MZ 용어 사전)","contents":"MZ세대가 최고로 사랑하는 대상, 1순위를 부르는 말.","retrieved":1716438075527},{"title":"undefined (Careet ─ Contents ─ MZ 용어 사전)","contents":"(one tool) 한 가지만 잘 한다는 말.","retrieved":1716438075528}]}