{"title":"Combined feed","url":"https://factcheckr.github.io/careet/all.xml","elements":[{"title":"undefined (Careet ─ Contents ─ MZ 용어 사전)","contents":"캐릭터 해석의 줄임말. 특정 인물을 분석해 나름의 이미지를 설정하는 일을 의미함.","retrieved":1729344308532},{"title":"undefined (Careet ─ Contents ─ MZ 용어 사전)","contents":"‘취업 뽀개기’의 줄임말. 취업에 성공했을 때 ‘취뽀했다’라고 함.","retrieved":1729344308534},{"title":"undefined (Careet ─ Contents ─ MZ 용어 사전)","contents":"‘광인’을 야민정음 방식으로 표기한 것. 특정 일에 미친듯이 몰두하는 사람을 지칭함.","retrieved":1729344308535},{"title":"undefined (Careet ─ Contents ─ MZ 용어 사전)","contents":"척척 박사를 변형한 신조어. 먹는 것에 진심인 사람들을 일컬음.","retrieved":1729344308536},{"title":"undefined (Careet ─ Contents ─ MZ 용어 사전)","contents":"박물관, 미술관 등에서 작품 등을 수집, 전시 기획 등을 하는 전문 직업.","retrieved":1729344308539},{"title":"undefined (Careet ─ Contents ─ MZ 용어 사전)","contents":"혼자 활동을 즐기는 사람을 부르는 말. 주로 게임과 관련해서 쓰임.","retrieved":1729344308539}]}