{"title":"Combined feed","url":"https://factcheckr.github.io/careet/all.xml","elements":[{"title":"undefined (Careet ─ Contents ─ MZ 용어 사전)","contents":"돈이 들어오는 시스템, 수입원.","retrieved":1721416640127},{"title":"undefined (Careet ─ Contents ─ MZ 용어 사전)","contents":"‘구독 파티원’의 줄임말. 구독료를 1/N 내고 사용하기 위해 여러 명이서 구독 서비스를 신청하는 MZ세대 문화를 나타냄.","retrieved":1721416640127},{"title":"undefined (Careet ─ Contents ─ MZ 용어 사전)","contents":"패션 트렌드 중 하나로, 브랜드 로고를 활용해 의상이나 액세서리를 디자인하는 것을 일컫는 말.","retrieved":1721416640129},{"title":"undefined (Careet ─ Contents ─ MZ 용어 사전)","contents":"King +‘열받네’의 합성어. 기본적으로 열받는다는 의미지만, Z세대 사이에선 다양한 의미로 활용됨.","retrieved":1721416640130},{"title":"undefined (Careet ─ Contents ─ MZ 용어 사전)","contents":"‘저녁 메뉴 추천’의 줄임말. 뭘 먹으면 좋을지 상대에게 메뉴를 추천 받을 때 사용함. 비슷한 용어로 ‘점메추(점심 메뉴 추천)’가 있음.","retrieved":1721416640131},{"title":"undefined (Careet ─ Contents ─ MZ 용어 사전)","contents":"하나의 게시물 안에서 주제를 정해놓고 댓글로 의견을 주고받는 커뮤니티 문화.","retrieved":1721416640132}]}