{"title":"Combined feed","url":"https://factcheckr.github.io/careet/all.xml","elements":[{"title":"undefined (Careet ─ Contents ─ MZ 용어 사전)","contents":"집에서 술을 마시는 것. 코로나19 이후 증가한 트렌드.","retrieved":1708417253634},{"title":"undefined (Careet ─ Contents ─ MZ 용어 사전)","contents":"10대 50여 명, 20대(27세 이하) 100여 명으로 구성된 캐릿의 트렌드 자문 그룹. MZ세대만 아는 문화, 유행을 발 빠르게 전하는 역할을 맡고 있음.","retrieved":1708417253635},{"title":"undefined (Careet ─ Contents ─ MZ 용어 사전)","contents":"‘사람 by 사람’의 줄임말. 사람마다 다 다르다는 것을 의미함.","retrieved":1708417253637},{"title":"undefined (Careet ─ Contents ─ MZ 용어 사전)","contents":"‘소소하지만 확실한 성취감’의 줄임말.","retrieved":1708417253638},{"title":"undefined (Careet ─ Contents ─ MZ 용어 사전)","contents":"Modify(수정하다)와 Consumer(소비자)의 합성어. 제조업체가 제공한 조리법을 따르지 않고 자신이 재창조한 방법으로 제품을 즐기는 소비자를 의미.","retrieved":1708417253639},{"title":"undefined (Careet ─ Contents ─ MZ 용어 사전)","contents":"네이버의 실시간 방송 플랫폼. 스타와 팬과 소통하는 창구로 쓰임.","retrieved":1708417253640}]}