{"title":"Combined feed","url":"https://factcheckr.github.io/careet/all.xml","elements":[{"title":"undefined (Careet ─ Contents ─ MZ 용어 사전)","contents":"‘캘린더’와 ‘박제’의 줄임말. 중요한 일정을 캘린더에 저장해둔다는 뜻임.","retrieved":1732231304353},{"title":"undefined (Careet ─ Contents ─ MZ 용어 사전)","contents":"‘프로필 사진’의 줄임말.","retrieved":1732231304354},{"title":"undefined (Careet ─ Contents ─ MZ 용어 사전)","contents":"온라인에서 널리 쓰이는 밈이 아닌, 특정 트위치 스트리머가 진행하는 방송에서만 사용되는 밈. 마치 내수(국내 수요, Domestic)용 제품처럼 특정한 사람들만 사용하고 외부로 확장되지 않는다는 뜻에서 붙여진 말.","retrieved":1732231304355},{"title":"undefined (Careet ─ Contents ─ MZ 용어 사전)","contents":"‘아무 것도 묻지도 따지지도 않고’의 줄임 말. 유명 광고에서 유래한 Z세대 유행어.","retrieved":1732231304357},{"title":"undefined (Careet ─ Contents ─ MZ 용어 사전)","contents":"근거 없는 자신감의 줄임말.","retrieved":1732231304358},{"title":"undefined (Careet ─ Contents ─ MZ 용어 사전)","contents":"라이브 방송의 줄임말.","retrieved":1732231304359}]}