{"title":"Combined feed","url":"https://factcheckr.github.io/careet/all.xml","elements":[{"title":"undefined (Careet ─ Contents ─ MZ 용어 사전)","contents":"‘순간’을 뜻하는 영어 단어인 ‘moment’를 그대로 발음한 말. 특정한 모습이나 행동을 보여주는 순간들을 강조할 때 사용함. [용례] ‘OO적 모먼트’","retrieved":1707844481938},{"title":"undefined (Careet ─ Contents ─ MZ 용어 사전)","contents":"‘홈 트레이닝’의 줄임말. 집에서 운동하는 것을 뜻함.","retrieved":1707844481939},{"title":"undefined (Careet ─ Contents ─ MZ 용어 사전)","contents":"‘페이스북 스토리 읽으면 페메(페북 메신저) 보낸다’의 줄임말.","retrieved":1707844481941},{"title":"undefined (Careet ─ Contents ─ MZ 용어 사전)","contents":"무료배송의 줄임말.","retrieved":1707844481942},{"title":"undefined (Careet ─ Contents ─ MZ 용어 사전)","contents":"‘진짜 텐션’의 줄임말. 꾸미지 않은 솔직한 분위기와 기분이 느껴진다는 뜻. 반대말은 ‘억텐(=억지 텐션)’.","retrieved":1707844481943},{"title":"undefined (Careet ─ Contents ─ MZ 용어 사전)","contents":"유튜브 영상에서 특정 구간으로 바로 이동할 수 있도록 설명 란이나 댓글에 시간을 표시해 두는 기능.","retrieved":1707844481944}]}