{"title":"Combined feed","url":"https://factcheckr.github.io/careet/all.xml","elements":[{"title":"undefined (Careet ─ Contents ─ MZ 용어 사전)","contents":"온라인에서 널리 쓰이는 밈이 아닌, 특정 트위치 스트리머가 진행하는 방송에서만 사용되는 밈. 마치 내수(국내 수요, Domestic)용 제품처럼 특정한 사람들만 사용하고 외부로 확장되지 않는다는 뜻에서 붙여진 말.","retrieved":1730755185785},{"title":"undefined (Careet ─ Contents ─ MZ 용어 사전)","contents":"‘입을 틀어 막다’의 줄임말. 주로 감정이 복받쳐 오를 때 사용함.","retrieved":1730755185785},{"title":"undefined (Careet ─ Contents ─ MZ 용어 사전)","contents":"직접 현장에 찾아가 운동 경기 등을 관람하는 일 ↔집관(집에서 관람)","retrieved":1730755185786},{"title":"undefined (Careet ─ Contents ─ MZ 용어 사전)","contents":"2000년대를 연상시키는 아날로그 감성의 촬영법. 주로 캠코더로 촬영한 듯한 저화질의 영상을 가리킴.","retrieved":1730755185787},{"title":"undefined (Careet ─ Contents ─ MZ 용어 사전)","contents":"안면이 없다는 뜻의 ‘초면’과 ‘멘션을 합친 트위터 용어.","retrieved":1730755185788},{"title":"undefined (Careet ─ Contents ─ MZ 용어 사전)","contents":"‘코스튬 플레이(costume play)’의 줄임말. 게임·만화 속 캐릭터로 분장하고, 그들과 비슷한 행동을 흉내내는 것을 뜻함. 넓게는 누군가를 흉내내는 것에도 코스프레라는 단어를 활용함.","retrieved":1730755185789}]}