{"title":"Combined feed","url":"https://factcheckr.github.io/careet/all.xml","elements":[{"title":"undefined (Careet ─ Contents ─ MZ 용어 사전)","contents":"짬에서 나오는 바이브의 줄임말. 연륜과 비슷한 의미로 사용됨.","retrieved":1716830198793},{"title":"undefined (Careet ─ Contents ─ MZ 용어 사전)","contents":"1020으로 구성된 캐릿의 해외 트렌드 자문 그룹. 해외 각국의 Z세대 트렌드를 발 빠르게 전하는 역할을 맡고 있음.","retrieved":1716830198793},{"title":"undefined (Careet ─ Contents ─ MZ 용어 사전)","contents":"트윗의 리트윗(공유) 수가 1,000 단위를 넘어가며 화제가 되는 경우, 해당 트윗을 올린 트위터리안을 부르는 말.","retrieved":1716830198795},{"title":"undefined (Careet ─ Contents ─ MZ 용어 사전)","contents":"알파 세대 유행어. ‘어쩌라고, TV나 봐’라는 의미로 추정됨.","retrieved":1716830198795},{"title":"undefined (Careet ─ Contents ─ MZ 용어 사전)","contents":"유명인이 자신의 성명이나 초상을 상품 등의 선전에 이용하는 것을 허락하는 권리.","retrieved":1716830198796},{"title":"undefined (Careet ─ Contents ─ MZ 용어 사전)","contents":"‘아트’와 ‘재테크’의 합성어. 미술 작품, 음악 저작권 등 다양한 예술 분야에 자산을 투자하는 방식을 말함.","retrieved":1716830198797}]}