{"title":"Combined feed","url":"https://factcheckr.github.io/careet/all.xml","elements":[{"title":"undefined (Careet ─ Contents ─ MZ 용어 사전)","contents":"‘홈 트레이닝’의 줄임말. 집에서 운동하는 것을 뜻함.","retrieved":1715505458631},{"title":"undefined (Careet ─ Contents ─ MZ 용어 사전)","contents":"인스타그램에서 2021년 출시한 숏폼 서비스.","retrieved":1715505458633},{"title":"undefined (Careet ─ Contents ─ MZ 용어 사전)","contents":"‘야구 푸드’의 줄임말. 야구 경기를 관람하면서 먹는 음식을 부르는 Z세대 신조어.","retrieved":1715505458634},{"title":"undefined (Careet ─ Contents ─ MZ 용어 사전)","contents":"인체에 분비되는 신경전달물질로 쾌락을 느끼게 해주는 것으로 알려져 있음.","retrieved":1715505458635},{"title":"undefined (Careet ─ Contents ─ MZ 용어 사전)","contents":"코로나 시국의 줄임말.","retrieved":1715505458637},{"title":"undefined (Careet ─ Contents ─ MZ 용어 사전)","contents":"레전드(Legend)의 D를 O로 잘못 읽은 말. 게임 스트리머 우왁굳의 방송에서 유래한 유행어.","retrieved":1715505458638}]}