{"title":"Combined feed","url":"https://factcheckr.github.io/careet/all.xml","elements":[{"title":"undefined (Careet ─ Contents ─ MZ 용어 사전)","contents":"웃음 소리를 나타낸 유행어 ‘ㅋㅋ루삥뽕’을 변형해서 쓰는 말.","retrieved":1719508744996},{"title":"undefined (Careet ─ Contents ─ MZ 용어 사전)","contents":"네이버, 카카오, 라인, 배달의민족, 당근마켓, 토스 등 신흥 IT 기업을 통칭하는 말. MZ세대 취업 준비생들이 입사하고 싶어하는 꿈의 직장으로 떠오르는 기업들.","retrieved":1719508744997},{"title":"undefined (Careet ─ Contents ─ MZ 용어 사전)","contents":"집에서 하는 요리.","retrieved":1719508744998},{"title":"undefined (Careet ─ Contents ─ MZ 용어 사전)","contents":"트위터 친구의 줄임말.","retrieved":1719508744999},{"title":"undefined (Careet ─ Contents ─ MZ 용어 사전)","contents":"King +‘인정’의 합성어. 강한 인정을 의미함","retrieved":1719508745000},{"title":"undefined (Careet ─ Contents ─ MZ 용어 사전)","contents":"숙박이 아닌 다른 목적으로 낮 시간 호캉스를 즐기는 문화.","retrieved":1719508745002}]}