{"title":"Careet ─ Contents ─ MZ 용어 사전","url":"https://www.careet.net/Dictionary","favicon":"https://www.careet.net/content/images/favicon.ico","elements":[{"contents":"[밈] 아이돌 그룹 ‘CIX’ 멤버가 ‘어여자(얼른 자)’라고 하면 팬들이 ‘어남자’라고 답하며 말장난한 것에서 유래. 2023년 말부터, 팬덤 내에서 소소하게 유행 중. (2024년 5월 기준)","retrieved":1732703086171},{"contents":"패션 트렌드 중 하나로, 브랜드 로고를 활용해 의상이나 액세서리를 디자인하는 것을 일컫는 말.","retrieved":1732703086172},{"contents":"생일 카페의 줄임말. 주로 아이돌의 생일을 기념하기 위해 열리며, 카페를 대관해 컵홀더 및 카페 내부를 아이돌 사진으로 꾸밈.","retrieved":1732703086173},{"contents":"‘합리적 의심’에 접두어 ‘킹’과 ‘갓’을 붙여 강조한 신조어.","retrieved":1732703086174},{"contents":"‘새롭고 놀랍다’란 뜻으로 신기하면서도 참신한 경우에 사용되는 신조어.","retrieved":1732703086175},{"contents":"식사(meal)와 준비(preparation)의 합성어. 최대 일주일치 식사를 미리 준비해뒀다가 식사 때마다 먹는 방법.","retrieved":1732703086177}]}