{"title":"Careet ─ Contents ─ MZ 용어 사전","url":"https://www.careet.net/Dictionary","favicon":"https://www.careet.net/content/images/favicon.ico","elements":[{"title":"술터뷰","contents":"‘술을 마시면서 진행하는 인터뷰’라는 뜻.","retrieved":1680340598787},{"title":"굿즈","contents":"원래 연예인과 관련된 사진, 포토카드, 응원봉 등의 제품을 뜻했으나, 최근엔 ‘한정판으로 출시되는 매력적인 아이템’을 통칭하는 단어로 자리잡음.","retrieved":1680340598789},{"title":"공구","contents":"공동구매의 줄임말. 유튜버나 인플루언서가 기성 브랜드 제품을 홍보하고, 공동구매 방식으로 판매까지 유도하는 마케팅 수단.","retrieved":1680340598790},{"title":"맞춤형 광고","contents":"이용자의 검색 기록, 구매 정보 등을 기반으로 노출되는 타깃 광고,","retrieved":1680340598792},{"title":"캐해석","contents":"캐릭터 해석의 줄임말. 특정 인물을 분석해 나름의 이미지를 설정하는 일을 의미함.","retrieved":1680340598794},{"title":"시강","contents":"‘시선 강탈’의 줄임말. 유독 남들의 시선(이목)을 끄는 것을 의미함.","retrieved":1680340598795}]}