{"title":"Careet ─ Contents ─ MZ 용어 사전","url":"https://www.careet.net/Dictionary","favicon":"https://www.careet.net/content/images/favicon.ico","elements":[{"title":"맞춤형 광고","contents":"이용자의 검색 기록, 구매 정보 등을 기반으로 노출되는 타깃 광고,","retrieved":1663284497796},{"title":"하이라이트","contents":"인스타 스토리를 프로필란에 고정할 수 있는 기능.","retrieved":1663284497796},{"title":"버블","contents":"스타와 마치 1:1 메시지를 주고받는 것처럼 소통할 수 있게 만들어진 프라이빗 메시지 앱. 유료로 이용이 가능하며 아이돌 팬덤이 활발하게 이용하는 서비스로 유명함.","retrieved":1663284497797},{"title":"하울(haul)","contents":"구매한 물건을 보여주면서 품평하는 유튜브 콘텐츠 포맷.","retrieved":1663284497798},{"title":"프사","contents":"‘프로필 사진’의 줄임말.","retrieved":1663284497801},{"title":"슈스","contents":"슈퍼스타의 줄임말.","retrieved":1663284497802}]}