{"title":"Careet ─ Contents ─ MZ 용어 사전","url":"https://www.careet.net/Dictionary","favicon":"https://www.careet.net/content/images/favicon.ico","elements":[{"title":"불판","contents":"하나의 게시물 안에서 주제를 정해놓고 댓글로 의견을 주고받는 커뮤니티 문화.","retrieved":1654360120468},{"title":"인급동","contents":"‘인기 급상승 동영상’의 줄임말. 유튜브에서 단시간에 높은 조회 수를 기록하고, 화제가 된 영상을 일컬음.","retrieved":1654360120470},{"title":"실감세대","contents":"실감나는 경험을 선호하고 소비함으로써, 내가 지금 이곳에 존재하고 있음을 실감하는 세대.","retrieved":1654360120471},{"title":"레게노","contents":"레전드(Legend)의 D를 O로 잘못 읽은 말. 스트리밍 방송에서 유래한 유행어.","retrieved":1654360120477},{"title":"맘찍","contents":"마음(=하트 버튼)을 찍어둔다는 뜻. 트위터에서 남의 게시물에 공감을 표하거나, 그 게시물을 보관하고 싶을 때 사용하는 기능.","retrieved":1654360120479},{"title":"포카 슬리브","contents":"포토카드 사이즈로 제작된 얇은 포장용 비닐.","retrieved":1654360120480}]}