{"title":"Careet ─ Contents ─ MZ 용어 사전","url":"https://www.careet.net/Dictionary","favicon":"https://www.careet.net/content/images/favicon.ico","elements":[{"title":"밀키트(meal kit)","contents":"레시피에 따라 미리 손질된 식재료가 팩에 들어있는 제품.","retrieved":1698736566408},{"title":"팬싸","contents":"팬 사인회의 줄임말.","retrieved":1698736566411},{"title":"실친","contents":"실제 친구의 줄임말. 온라인에서 사귄 친구가 아니라는 뜻.","retrieved":1698736566412},{"title":"트롤","contents":"온라인에서 사람들의 관심을 끌기 위해 일부러 진행에 방해되는 행동을 하는 것. 또는 그런 사람을 뜻함.","retrieved":1698736566413},{"title":"펀슈머","contents":"‘Fun(재미)’과 ‘Consumer(소비자)’의 합성어로, 소비 과정에서 재미를 추구하는 소비자를 일컫는 말.","retrieved":1698736566414},{"title":"즈즈즈","contents":"아이돌 그룹 ‘더보이즈’, ‘스트레이키즈’, ‘에이티즈’를 합쳐 부르는 말.","retrieved":1698736566415}]}