{"title":"Careet ─ Contents ─ MZ 용어 사전","url":"https://www.careet.net/Dictionary","favicon":"https://www.careet.net/content/images/favicon.ico","elements":[{"title":"네카라쿠배당토","contents":"네이버, 카카오, 라인, 배달의민족, 당근마켓, 토스 등 신흥 IT 기업을 통칭하는 말. MZ세대 취업 준비생들이 입사하고 싶어하는 꿈의 직장으로 떠오르는 기업들.","retrieved":1688480303180},{"title":"버실","contents":"버전 실시간의 줄임말. 슬라임 영상에 상황극 음성이나 자막을 입힌 콘텐츠를 말함.","retrieved":1688480303180},{"title":"처돌이","contents":"치킨 브랜드 ‘처갓집’의 마스코트 ‘처돌이’에서 유래한 말. 특정 대상을 매우 좋아한다는 뜻.","retrieved":1688480303181},{"title":"덕력","contents":"덕후+力(힘)의 합성어로, 팬심이 깊은 사람에게 덕력이 높다는 표현을 씀.","retrieved":1688480303182},{"title":"쓸디계","contents":"3D 계정의 줄임말. 2D 애니메이션 캐릭터가 아닌, 실제 인물을 덕질하는 계정을 일컫는 말.","retrieved":1688480303183},{"title":"스카","contents":"스터디 카페의 줄임말.","retrieved":1688480303184}]}