{"title":"Careet ─ Contents ─ MZ 용어 사전","url":"https://www.careet.net/Dictionary","favicon":"https://www.careet.net/content/images/favicon.ico","elements":[{"title":"띵 소비","contents":"이미 소분된 제품을 구매하거나, 대용량 제품을 구입해서 여러 사람과 셀프로 나누는 소비 방식.","retrieved":1705101419747},{"title":"온콘","contents":"온라인 콘서트의 줄임말.","retrieved":1705101419748},{"title":"네카라쿠배당토","contents":"네이버, 카카오, 라인, 배달의민족, 당근마켓, 토스 등 신흥 IT 기업을 통칭하는 말. MZ세대 취업 준비생들이 입사하고 싶어하는 꿈의 직장으로 떠오르는 기업들.","retrieved":1705101419748},{"title":"한줌단","contents":"다 모아도 한 줌이 될 것 같은 적은 수의 집단을 부르는 말. MZ세대가 비주류를 지칭할 때 사용함.","retrieved":1705101419750},{"title":"취준","contents":"‘취업 준비’의 줄임말.","retrieved":1705101419752},{"title":"공구","contents":"공동구매의 줄임말. 비용 절감 등을 이유로 특정 물건을 단체로 사는 구매 방식.","retrieved":1705101419753}]}