{"title":"Careet ─ Contents ─ MZ 용어 사전","url":"https://www.careet.net/Dictionary","favicon":"https://www.careet.net/content/images/favicon.ico","elements":[{"title":"미공포","contents":"‘미공개 포토카드’의 줄임말. 앨범에 수록된 ‘공식 포토카드’를 제외한 포토카드를 일컬음. 보통 아이돌 팬들이 각종 이벤트에 참여해서 받게 되는 경우가 많음.","retrieved":1705054766500},{"title":"인친","contents":"인스타그램 친구의 줄임말.","retrieved":1705054766505},{"title":"넘사벽","contents":"넘을 수 없는 4차원의 벽의 줄임말. 대상과 거리감이 많이 느껴질 때 주로 사용함.","retrieved":1705054766512},{"title":"드볼","contents":"포카, 스티커 등 여러 종으로 나온 굿즈를 모두 모으는 것을 만화 &lt;드래곤 볼&gt;에 빗대어 부르는 말.","retrieved":1705054766513},{"title":"밥약","contents":"밥 약속의 줄임 말.","retrieved":1705054766513},{"title":"뉴노멀(New normal)","contents":"상황 변화에 따라 과거의 표준이 더 이상 통하지 않고 새로운 가치 표준이 세상 변화를 주도하는 상태.","retrieved":1705054766513}]}