{"title":"Careet ─ Contents ─ MZ 용어 사전","url":"https://www.careet.net/Dictionary","favicon":"https://www.careet.net/content/images/favicon.ico","elements":[{"title":"민초단","contents":"민트 초코를 좋아하는 이들을 부르는 말. 호불호가 갈리는 민트 초코 논쟁에서 ‘민초’ 편인 사람.","retrieved":1663525791527},{"title":"이때싶","contents":"'이때다 싶어'의 줄임말. 물 들어올 때 노 젓는다는 뜻.","retrieved":1663525791528},{"title":"광클","contents":"‘狂+click’의 줄임말. 아주 빠른 속도로 클릭하는 것을 의미함.","retrieved":1663525791531},{"title":"온콘","contents":"온라인 콘서트의 줄임말.","retrieved":1663525791532},{"title":"펀슈머","contents":"‘Fun(재미)’과 ‘Consumer(소비자)’의 합성어로, 소비 과정에서 재미를 추구하는 소비자를 일컫는 말.","retrieved":1663525791532},{"title":"내돈내산","contents":"‘내 돈으로 내가 산’의 줄임말. 주로 제품 리뷰를 할 때 광고가 아니라는 것을 강조하기 위해 사용함.","retrieved":1663525791533}]}