{"title":"Careet ─ Contents ─ MZ 용어 사전","url":"https://www.careet.net/Dictionary","favicon":"https://www.careet.net/content/images/favicon.ico","elements":[{"contents":"‘갑자기 툭 튀어나오다’의 줄임말","retrieved":1721543209089},{"contents":"학습지 이름 ‘씽크빅’에서 유래한 표현. 창의력이 뛰어난 대상을 칭찬할 때 쓰인다. “어릴 때 씽크빅 좀 했나 봐?”라는 문장에서 파생돼 “오, 씽크빅!”같은 감탄사로도 쓰임.","retrieved":1721543209090},{"contents":"소원 성취의 줄임말. ‘바라다’라는 뜻의 신조어.","retrieved":1721543209091},{"contents":"교육 분야에서 활동하는 연예인 또는 엔터테이너. 에듀케이션(Education)과 엔터테이너(Entertainer)의 합성어.","retrieved":1721543209092},{"contents":"공동구매의 줄임말. 비용 절감 등을 이유로 특정 물건을 단체로 사는 구매 방식.","retrieved":1721543209094},{"contents":"‘시즌그리팅’의 줄임말. 새해를 맞아 판매되는 달력, 다이어리 등의 굿즈 세트.","retrieved":1721543209095}]}