{"title":"Careet ─ Contents ─ MZ 용어 사전","url":"https://www.careet.net/Dictionary","favicon":"https://www.careet.net/content/images/favicon.ico","elements":[{"title":"로고 플레이","contents":"패션 트렌드 중 하나로, 브랜드 로고를 활용해 의상이나 액세서리를 디자인하는 것을 일컫는 말.","retrieved":1673504657747},{"title":"카공","contents":"카페에서 공부하는 것의 줄임말.","retrieved":1673504657749},{"title":"미슐랭","contents":"특정 대상을 칭찬할 때 쓰이는 ‘OO 맛집이다’라는 표현이 변형된 버전. ex) “캐릿 트렌드 미슐랭이네”","retrieved":1673504657752},{"title":"ㄱㅇㅇ","contents":"‘귀여워’를 초성만으로 표현한 단어.","retrieved":1673504657753},{"title":"얼빡","contents":"얼굴이 한 프레임에 가득 찼다는 뜻. 이렇게 나온 사진을 ‘얼빡샷’이라고 부름.","retrieved":1673504657753},{"title":"맵부심","contents":"‘맵(다)’+‘자부심’의 합성어. 매운 것을 잘 먹는 데 자부심이 있음을 뜻하는 말.","retrieved":1673504657753}]}