{"title":"Careet ─ Contents ─ MZ 용어 사전","url":"https://www.careet.net/Dictionary","favicon":"https://www.careet.net/content/images/favicon.ico","elements":[{"contents":"웃음 소리를 나타낸 유행어 ‘ㅋㅋ루삥뽕’을 변형해서 쓰는 말.","retrieved":1707660932179},{"contents":"‘상상 플레이’의 줄임말. MZ세대가 썰을 풀고 노는 문화를 칭하는 말.","retrieved":1707660932181},{"contents":"폰꾸미기의 줄임말. 주로 휴대폰 배경화면이나 앱 아이콘을 커스텀 하는 것을 뜻함.","retrieved":1707660932182},{"contents":"god(신)과 인생이 합쳐진 단어로, 부지런하고 알찬 삶을 사는 것을 일컫는 말.","retrieved":1707660932183},{"contents":"아이돌 멤버의 사진으로 만든 카드로, 주로 앨범 당 한 장씩 들어있는 굿즈. 줄여서 ‘포카’라고 부름.","retrieved":1707660932184},{"contents":"‘뇌+에이징’의 합성어. 처음 봤을 때 이상하던 디자인이 보면 볼수록 예뻐 보일 때 사용함.","retrieved":1707660932185}]}