{"title":"Careet ─ Contents ─ MZ 용어 사전","url":"https://www.careet.net/Dictionary","favicon":"https://www.careet.net/content/images/favicon.ico","elements":[{"contents":"아이돌과 닮은 캐릭터를 활용해 만든 10cm 크기의 작은 인형","retrieved":1733661687751},{"contents":"‘마음에 상처가 났다’는 뜻 .","retrieved":1733661687753},{"contents":"인스타그램에 연재되는 만화(Cartoon)의 줄임말.","retrieved":1733661687754},{"contents":"기존 데이터와 비교 학습을 통해 새로운 창작물을 탄생시키는 인공지능을 뜻함","retrieved":1733661687755},{"contents":"'기분 좋은 소름'을 뜻하는 ASMR 용어.","retrieved":1733661687756},{"contents":"헤어 메이크업 코디를 합쳐 부르는 말","retrieved":1733661687757}]}