{"title":"Careet ─ Contents ─ MZ 용어 사전","url":"https://www.careet.net/Dictionary","favicon":"https://www.careet.net/content/images/favicon.ico","elements":[{"title":"재질","contents":"느낌, 톤, 성향을 이르는 MZ세대 유행어.","retrieved":1660173718865},{"title":"인용 알티","contents":"트위터에서 다른 사람의 트윗 위에 자신의 의견을 덧붙여서 공유하는 기능.","retrieved":1660173718867},{"title":"코 세 글자","contents":"MZ세대가 코로나19를 일컫는 말. 트위터에서 ‘코로나’라는 단어를 사용하면 계정이 잠기는 일이 발생해 코로나를 대체하는 표현으로 사용되기 시작함.","retrieved":1660173718868},{"title":"맛집","contents":"‘이 집 잘한다’는 칭찬의 표현. ‘엔딩 맛집’, ‘케미(합) 맛집’ 등 다양한 단어 뒤에 붙임.","retrieved":1660173718870},{"title":"좋댓공","contents":"SNS 게시물에 좋아요 누르고, 공유하고, 댓글을 달아 달라는 뜻.","retrieved":1660173718871},{"title":"댈컴","contents":"‘대리 커스터마이징’의 줄임말. 대리로 남의 아바타를 디자인해주는 것을 뜻함.","retrieved":1660173718872}]}