{"title":"Careet ─ Contents ─ MZ 용어 사전","url":"https://www.careet.net/Dictionary","favicon":"https://www.careet.net/content/images/favicon.ico","elements":[{"contents":"스트리밍의 줄임말. 아이돌 팬들이 음원 사이트에서 응원하는 가수의 노래를 차트 1위로 만들어주기 위해 반복해서 듣는 것을 ‘스밍 돌린다’고 표현함.","retrieved":1712582359556},{"contents":"'기분 좋은 소름'을 뜻하는 ASMR 용어.","retrieved":1712582359556},{"contents":"유명인이 자신의 성명이나 초상을 상품 등의 선전에 이용하는 것을 허락하는 권리.","retrieved":1712582359558},{"contents":"(one tool) 한 가지만 잘 한다는 말.","retrieved":1712582359559},{"contents":"(공식적으로 촬영된 것이 아닌) 팬이 직접 찍은 사진.","retrieved":1712582359560},{"contents":"집순이의 반대말로, 밖에서 노는 걸 좋아하는 사람을 일컫는 말.","retrieved":1712582359561}]}