{"title":"Careet ─ Contents ─ MZ 용어 사전","url":"https://www.careet.net/Dictionary","favicon":"https://www.careet.net/content/images/favicon.ico","elements":[{"title":"인소","contents":"인터넷 소설의 줄임말.","retrieved":1660814620145},{"title":"어그로(aggro)","contents":"상대의 관심을 끌거나 도발하기 위해 자극적인 행동을 하는 것을 뜻하는 인터넷 용어.","retrieved":1660814620145},{"title":"퍼컬","contents":"‘퍼스널 컬러’의 줄임말. 퍼스널 컬러란, 개인의 피부톤에 어울리는 컬러를 뜻하는 말로 요즘 MZ세대는 자신의 퍼스널 컬러에 맞춰 의상, 화장품 등을 구입하려고 함.","retrieved":1660814620146},{"title":"파티원","contents":"게임 용어로 함께 퀘스트를 깨러 갈 팀원이라는 의미.","retrieved":1660814620147},{"title":"뉴노멀(New normal)","contents":"상황 변화에 따라 과거의 표준이 더 이상 통하지 않고 새로운 가치 표준이 세상 변화를 주도하는 상태.","retrieved":1660814620148},{"title":"슈스","contents":"슈퍼스타의 줄임말.","retrieved":1660814620149}]}