{"title":"Careet ─ Contents ─ MZ 용어 사전","url":"https://www.careet.net/Dictionary","favicon":"https://www.careet.net/content/images/favicon.ico","elements":[{"title":"일잘러","contents":"일 잘하는 사람을 뜻하는 신조어","retrieved":1699218941121},{"title":"VSCO","contents":"사진 보정 앱. 포토샵처럼 세세한 조절도 가능하다. 이런 감성을 묶어 부르는 VSCO girl이란 말도 있음.","retrieved":1699218941123},{"title":"인스타 스토리","contents":"인스타그램에서 24시간 동안만 공개되는 게시물. 개인의 피드에도 게시되지 않는 것이 특징.","retrieved":1699218941128},{"title":"합방","contents":"합동방송의 줄임말. 주로 인터넷 방송에서 합동 콘텐츠를 찍는 것을 부르는 말.","retrieved":1699218941131},{"title":"인장","contents":"트위터에서 ‘프로필 사진’을 일컫는 말. 프로필 사진이 올라가는 템플릿이 도장처럼 동그란 데서 유래한 별칭.","retrieved":1699218941134},{"title":"맘찍","contents":"마음(=하트 버튼)을 찍어둔다는 뜻. 트위터에서 남의 게시물에 공감을 표하거나, 그 게시물을 보관하고 싶을 때 사용하는 기능.","retrieved":1699218941136}]}