{"title":"Careet ─ Contents ─ MZ 용어 사전","url":"https://www.careet.net/Dictionary","favicon":"https://www.careet.net/content/images/favicon.ico","elements":[{"title":"가상 데스크톱 서비스","contents":"PC 환경을 온라인에 구축해 어디서든 접속할 수 있게 하는 서비스.","retrieved":1696929526539},{"title":"밀키트(meal kit)","contents":"레시피에 따라 미리 손질된 식재료가 팩에 들어있는 제품.","retrieved":1696929526544},{"title":"알못","contents":"어떤 분야에 대해 잘 알지 못하는 사람을 부르는 말↔잘알","retrieved":1696929526550},{"title":"맛없없","contents":"‘맛 없을 수 없다’의 줄임말.","retrieved":1696929526552},{"title":"브이로그","contents":"브이로그(v-log): 비디오(video)와 블로그(blog)의 합성어. 자신의 일상을 영상으로 촬영한 콘텐츠를 말함.","retrieved":1696929526555},{"title":"피케팅","contents":"‘피 튀기는 경쟁률을 자랑하는 티케팅’의 줄임말.","retrieved":1696929526557}]}