{"title":"Careet ─ Contents ─ MZ 용어 사전","url":"https://www.careet.net/Dictionary","favicon":"https://www.careet.net/content/images/favicon.ico","elements":[{"title":"읽페","contents":"‘페이스북 스토리 읽으면 페메(페북 메신저) 보낸다’의 줄임말.","retrieved":1669447060347},{"title":"영통팬싸","contents":"영상 통화로 하는 팬 사인회의 줄임말. 코로나 사태 이후 활성화 된 비대면 팬 이벤트 종류의 하나.","retrieved":1669447060347},{"title":"구독팟","contents":"‘구독 파티원’의 줄임말. 구독료를 1/N 내고 사용하기 위해 여러 명이서 구독 서비스를 신청하는 MZ세대 문화를 나타냄.","retrieved":1669447060348},{"title":"입틀막","contents":"‘입을 틀어 막다’의 줄임말. 주로 감정이 복받쳐 오를 때 사용함.","retrieved":1669447060349},{"title":"다꾸","contents":"다이어리 꾸미기의 줄임말.","retrieved":1669447060350},{"title":"역조공","contents":"연예인이 자신의 팬들에게 선물을 주는 행동 혹은 그 선물을 가르키는 말.","retrieved":1669447060351}]}