{"title":"Careet ─ Contents ─ MZ 용어 사전","url":"https://www.careet.net/Dictionary","favicon":"https://www.careet.net/content/images/favicon.ico","elements":[{"contents":"스타와 마치 1:1 메시지를 주고받는 것처럼 소통할 수 있게 만들어진 프라이빗 메시지 앱. 유료로 이용이 가능하며 아이돌 팬덤이 활발하게 이용하는 서비스로 유명함.","retrieved":1726147586972},{"contents":"[밈] 아이돌 그룹 ‘CIX’ 멤버가 ‘어여자(얼른 자)’라고 하면 팬들이 ‘어남자’라고 답하며 말장난한 것에서 유래. 2023년 말부터, 팬덤 내에서 소소하게 유행 중. (2024년 5월 기준)","retrieved":1726147586972},{"contents":"1981년~1996년에 출생한 세대를 가리키는 말. 대학내일20대연구소에선 심리적, 사회적 동질성을 고려해 1989년 이전 출생자는 전기 밀레니얼, 1989년 출생자부터는 후기 밀레니얼로 구분하고 있음.","retrieved":1726147586973},{"contents":"1996년 이후 출생~2010년대 초반 출생자.","retrieved":1726147586974},{"contents":"Hot + ‘아이템’의 합성어. 유행하는 아이템이나 꼭 필요한 아이템을 뜻함.","retrieved":1726147586975},{"contents":"공병이 될 때까지 싹싹 긁어 쓸 정도로 잘 맞는 아이템이라는 뜻. 뷰티 카테고리에서 주로 쓰이는 표현.","retrieved":1726147586976}]}