{"title":"Careet ─ Contents ─ MZ 용어 사전","url":"https://www.careet.net/Dictionary","favicon":"https://www.careet.net/content/images/favicon.ico","elements":[{"title":"가심비","contents":"가격 대비 심리적 만족을 추구하는 소비 트렌드↔가성비","retrieved":1705645429093},{"title":"갓성비","contents":"대단한 존재를 ‘갓(god)+OO’이라고 부르는 MZ세대의 언어 습관에서 유래된 말로, 가성비를 뛰어넘는 혜택을 느낄 때 쓰는 말.","retrieved":1705645429095},{"title":"OO깡","contents":"덕질 용어에서 처음 시작된 단어로 깡은 깐다의 줄임말. 원하는 제품을 깐다는 말로 해석할 수 있다. 비슷한 단어로는 언박싱이 있다.","retrieved":1705645429096},{"title":"쩝쩝 박사","contents":"척척 박사를 변형한 신조어. 먹는 것에 진심인 사람들을 일컬음.","retrieved":1705645429097},{"title":"트친","contents":"트위터 친구의 줄임말.","retrieved":1705645429098},{"title":"레게노","contents":"레전드(Legend)의 D를 O로 잘못 읽은 말. 게임 스트리머 우왁굳의 방송에서 유래한 유행어.","retrieved":1705645429100}]}