{"title":"Careet ─ Contents ─ MZ 용어 사전","url":"https://www.careet.net/Dictionary","favicon":"https://www.careet.net/content/images/favicon.ico","elements":[{"contents":"(one tool) 한 가지만 잘 한다는 말.","retrieved":1721848565396},{"contents":"손재주가 영 없는 사람을 비유한 말. ↔ 유행어 ‘금손’","retrieved":1721848565397},{"contents":"영국 드라마 &lt;스킨스&gt;의 퇴폐적인 주인공을 따라하는 사람들을 일컫는 말. 2010년대에 창궐하다 사라졌음.","retrieved":1721848565398},{"contents":"원래는 채식주의 중에서도 가장 엄격한 단계를 뜻하는 단어지만, 요즘은 철학적인 이유로 동물성 식품을 섭취하지 않는 사람들을 통칭해 ‘비건’이라고 부르는 경우가 많음.","retrieved":1721848565400},{"contents":"콘텐츠나 이벤트 등에 숨겨진 메시지나 기능","retrieved":1721848565401},{"contents":"'기분 좋은 소름'을 뜻하는 ASMR 용어.","retrieved":1721848565402}]}