{"title":"Careet ─ Contents ─ MZ 용어 사전","url":"https://www.careet.net/Dictionary","favicon":"https://www.careet.net/content/images/favicon.ico","elements":[{"title":"프사","contents":"‘프로필 사진’의 줄임말.","retrieved":1682918246668},{"title":"혜자","contents":"가성비가 좋다, 넉넉하고 인심이 후하다는 뜻. 배우 김혜자가 모델이었던 편의점 도시락이 가성비가 좋았던 것에서 유래함.","retrieved":1682918246670},{"title":"장비병","contents":"무언가를 시작할 때 필요한 장비부터 구입하는 장비 덕후를 뜻하는 말.","retrieved":1682918246671},{"title":"반모","contents":"반말로 말하는 것. '반말 모드'의 줄임말.","retrieved":1682918246674},{"title":"플리","contents":"‘플레이리스트’의 줄임말","retrieved":1682918246676},{"title":"핀스타","contents":"가짜 계정. ‘Fake Instagram’의 줄임말.","retrieved":1682918246677}]}