{"title":"Careet ─ Contents ─ MZ 용어 사전","url":"https://www.careet.net/Dictionary","favicon":"https://www.careet.net/content/images/favicon.ico","elements":[{"title":"세포마켓","contents":"1인 미디어 시대에서 SNS를 통해 이뤄지는 1인 마켓. 기업 단위가 아닌 1인 사업자가 주를 이뤄 세포가 분열하는 것처럼 개인 단위로 발전하는 현상을 뜻함.","retrieved":1677047154825},{"title":"찐","contents":"‘진짜’를 뜻하는 접두어. ‘찐팬’, ‘찐사랑’ 등 진심을 강조하고 싶을 때 쓰임.","retrieved":1677047154827},{"title":"0차","contents":"1차로 방문할 예정인 핫플레이스에 웨이팅이 길 경우, 대기를 걸어두고 방문하는 주변 공간을 가리킴.","retrieved":1677047154829},{"title":"킬포","contents":"‘킬링 포인트’의 줄임말. ‘하이라이트’와 비슷한 의미로 사용됨.","retrieved":1677047154831},{"title":"신박한","contents":"‘새롭고 놀랍다’란 뜻으로 신기하면서도 참신한 경우에 사용되는 신조어.","retrieved":1677047154832},{"title":"로고 플레이","contents":"패션 트렌드 중 하나로, 브랜드 로고를 활용해 의상이나 액세서리를 디자인하는 것을 일컫는 말.","retrieved":1677047154835}]}