{"title":"Careet ─ Contents ─ MZ 용어 사전","url":"https://www.careet.net/Dictionary","favicon":"https://www.careet.net/content/images/favicon.ico","elements":[{"contents":"국내 굴지의 대기업인 삼성, 현대, SK, LG를 통칭하는 말. MZ세대 취업 준비생들이 입사하고 싶어하는 꿈의 직장으로 꼽히는 기업들.","retrieved":1713557866153},{"contents":"게임 용어로 함께 퀘스트를 깨러 갈 팀원이라는 의미.","retrieved":1713557866154},{"contents":"원래 캐릭터(‘본캐’)가 아닌 또 다른 캐릭터. 온라인 게임에서 유래한 말.","retrieved":1713557866156},{"contents":"‘할매’와 ‘밀레니얼’ 세대의 합성어. 레트로 취향의 음식과 패션을 선호하는 밀레니얼 세대를 의미.","retrieved":1713557866156},{"contents":"‘자체 제작 컨텐츠’의 줄임말. 방송사가 아닌 소속사가 직접 제작하는 아티스트 관련 콘텐츠를 말함.","retrieved":1713557866157},{"contents":"국민 룰의 줄임말. 보편적으로 통용되는 규칙 혹은 유행이라는 뜻.","retrieved":1713557866158}]}