{"title":"Careet ─ Contents ─ MZ 용어 사전","url":"https://www.careet.net/Dictionary","favicon":"https://www.careet.net/content/images/favicon.ico","elements":[{"contents":"아웃도어 제품을 일상복과 매치하는 스타일.","retrieved":1719443975851},{"contents":"‘엄마 카드’ 등 부모님의 카드를 부르는 말.","retrieved":1719443975852},{"contents":"위장 꾸미기. 맛있는 식사를 하는 것을 꾸미기에 빗대어 부르는 말.","retrieved":1719443975854},{"contents":"특정 분야에 막대한 시간과 정성을 투자하여 경지에 이른 사람을 뜻함. ‘고수’, ‘헤비 유저’와 비슷한 의미.","retrieved":1719443975855},{"contents":"인터넷상에서, 불법으로 다른 사람의 게시물을 그대로 가져오거나 가져가는 일. ‘불법 퍼 옴’의 줄인 말이다.","retrieved":1719443975856},{"contents":"공병이 될 때까지 싹싹 긁어 쓸 정도로 잘 맞는 아이템이라는 뜻. 뷰티 카테고리에서 주로 쓰이는 표현.","retrieved":1719443975857}]}