{"title":"Careet ─ Contents ─ MZ 용어 사전","url":"https://www.careet.net/Dictionary","favicon":"https://www.careet.net/content/images/favicon.ico","elements":[{"contents":"군대와 공백기의 합성어. 군 복무로 인한 연예인의 공백기를 뜻함.","retrieved":1732472864982},{"contents":"믹스견을 뜻하는 말. ‘시골 잡종’을 외국어처럼 받침을 길게 늘려 발음한 것.","retrieved":1732472864983},{"contents":"'잘 안다', '잘 아는 사람'이라는 뜻의 신조어.","retrieved":1732472864984},{"contents":"King +‘인정’의 합성어. 강한 인정을 의미함","retrieved":1732472864985},{"contents":"‘프로필 사진’의 줄임말.","retrieved":1732472864987},{"contents":"~에 대해 집착이 있는 사람을 뜻하는 MZ세대의 신조어.","retrieved":1732472864988}]}