{"title":"Careet ─ Contents ─ MZ 용어 사전","url":"https://www.careet.net/Dictionary","favicon":"https://www.careet.net/content/images/favicon.ico","elements":[{"title":"RT","contents":"‘리트윗(Re Tweet)’의 약자. 트위터에서 다른 계정의 게시물을 자신의 계정에 공유하는 기능을 의미함.","retrieved":1654609437556},{"title":"안읽씹","contents":"메시지를 읽지도 않고 답장도 하지 않는 경우를 일컫는 표현.","retrieved":1654609437556},{"title":"킬포","contents":"‘킬링 포인트’의 줄임말. ‘하이라이트’와 비슷한 의미로 사용됨.","retrieved":1654609437556},{"title":"인스타그래머","contents":"인스타그램을 하는 사람을 일컫는 말. 주로 인스타그램에 트렌디한 게시물을 자주 올리는 사람이라는 의미로 쓰임.","retrieved":1654609437557},{"title":"온클","contents":"‘온라인 클래스’의 줄임말.","retrieved":1654609437560},{"title":"좋댓구알","contents":"좋아요, 댓글, 구독, 알림설정의 줄임말","retrieved":1654609437560}]}