{"title":"Careet ─ Contents ─ MZ 용어 사전","url":"https://www.careet.net/Dictionary","favicon":"https://www.careet.net/content/images/favicon.ico","elements":[{"title":"좋댓구알","contents":"좋아요, 댓글, 구독, 알림설정의 줄임말","retrieved":1697537986381},{"title":"도무송","contents":"칼선이 들어가 모양대로 뗄 수 있는 스티커. 일반적으로 한 장에 스티커 하나씩 들어가 있는 형태가 많음.","retrieved":1697537986384},{"title":"하이라이트","contents":"인스타 스토리를 프로필란에 고정할 수 있는 기능.","retrieved":1697537986389},{"title":"직접 추가","contents":"인스타그램에서 다른 사용자가 올린 게시물과 엮어서 새로운 게시물을 올릴 수 있는 기능.","retrieved":1697537986392},{"title":"임플로이언서","contents":"Employee+Influencer. 직원으로서 기업의 브랜딩과 이미지에 영향력을 미치는 존재.","retrieved":1697537986395},{"title":"알못","contents":"어떤 분야에 대해 잘 알지 못하는 사람을 부르는 말↔잘알","retrieved":1697537986397}]}