{"title":"Careet ─ Contents ─ MZ 용어 사전","url":"https://www.careet.net/Dictionary","favicon":"https://www.careet.net/content/images/favicon.ico","elements":[{"title":"밸런스 게임","contents":"쉽게 고를 수 없는 두 가지 상황을 제시하고, 뭐가 더 나은지 선택하는 게임. 용례: 카레맛 똥 VS 똥맛 카레","retrieved":1669803840427},{"title":"야민정음","contents":"야구 갤러리+훈민정음의 합성어. 디시인사이드 야구 갤러리에서 만든 드립으로 원래 글자를 모양이 비슷한 다른 글자로 대체해 표기하는 방식. (ex. 멍멍이 → 댕댕이)","retrieved":1669803840429},{"title":"라라라러브송","contents":"일본인 가수 ‘쿠보타 토시노부’의 ‘La La La Love Song’. 시티팝 특유의 감성이 그대로 녹아 있는 유명곡 중 하나로 국내에서 많은 아티스트가 커버함","retrieved":1669803840431},{"title":"인쇼","contents":"‘인터넷 쇼핑’의 줄임말.","retrieved":1669803840433},{"title":"팅글","contents":"'기분 좋은 소름'을 뜻하는 ASMR 용어.","retrieved":1669803840435},{"title":"콜렉트북","contents":"포토카드나 사진을 모아두는 앨범","retrieved":1669803840437}]}