{"title":"Careet ─ Contents ─ MZ 용어 사전","url":"https://www.careet.net/Dictionary","favicon":"https://www.careet.net/content/images/favicon.ico","elements":[{"title":"인싸","contents":"‘인사이더(insider)’를 줄인 한국식 영어 표현. 사람들과 잘 어울리며 발이 넓은 사람을 뜻함.","retrieved":1662622595836},{"title":"쇼츠","contents":"유튜브에서 2021년 베타 출시한 숏폼 서비스.","retrieved":1662622595836},{"title":"옾챗","contents":"오픈채팅방의 Z세대식 줄임말. Z세대는 오픈채팅방을 커뮤니티처럼 이용함.","retrieved":1662622595838},{"title":"위버스","contents":"좋아하는 아티스트에게 글을 쓰고 사진을 남길 수 있는 소셜 네트워킹 앱.","retrieved":1662622595839},{"title":"포토 카드","contents":"아이돌 멤버의 사진으로 만든 카드로, 주로 앨범 당 한 장씩 들어있는 굿즈. 줄여서 ‘포카’라고 부름.","retrieved":1662622595840},{"title":"긱 이코노미","contents":"Gig Economy. 기업들이 필요에 따라 단기 계약직이나 임시직으로 인력을 충원하고 그 대가를 지불하는 형태의 경제.","retrieved":1662622595841}]}