{"title":"Careet ─ Contents ─ MZ 용어 사전","url":"https://www.careet.net/Dictionary","favicon":"https://www.careet.net/content/images/favicon.ico","elements":[{"contents":"‘순식간에 삭제되다’의 줄임말. ‘너무 재밌어서 시간 가는 줄 몰랐다’, ‘너무 맛있어서 순식간에 다 먹어 버렸다.’ 등의 맥락에서 사용됨.","retrieved":1713474965771},{"contents":"인스타그램에서 2021년 출시한 숏폼 서비스.","retrieved":1713474965772},{"contents":"대화가 없는 고독한 채팅방과 달리, 대화도 하며 특정 연예인의 짤(이미지)도 공유하는 카카오톡 오픈 채팅방.","retrieved":1713474965773},{"contents":"‘학대(cruelty)가 없다(free)’는 의미로, 동물 실험을 하지 않거나 동물 유래 원료를 사용하지 않은 제품을 뜻함.","retrieved":1713474965776},{"contents":"‘맛 없을 수 없다’의 줄임말.","retrieved":1713474965777},{"contents":"사진 보정 앱. 포토샵처럼 세세한 조절도 가능하다. 이런 감성을 묶어 부르는 VSCO girl이란 말도 있음.","retrieved":1713474965779}]}