{"title":"Careet ─ Contents ─ MZ 용어 사전","url":"https://www.careet.net/Dictionary","favicon":"https://www.careet.net/content/images/favicon.ico","elements":[{"title":"스불재","contents":"‘스스로 불러온 재앙에 짓눌려’의 준말. 노래 Lazenca, save us에서 탄생한 밈.","retrieved":1677442817619},{"title":"뉴짤","contents":"새로 뜬 사진, 새로 뜬 gif","retrieved":1677442817621},{"title":"아묻따","contents":"‘아무 것도 묻지도 따지지도 않고’의 줄임 말. 유명 광고에서 유래한 Z세대 유행어.","retrieved":1677442817622},{"title":"라라라러브송","contents":"일본인 가수 ‘쿠보타 토시노부’의 ‘La La La Love Song’. 시티팝 특유의 감성이 그대로 녹아 있는 유명곡 중 하나로 국내에서 많은 아티스트가 커버함","retrieved":1677442817623},{"title":"폰꾸","contents":"폰꾸미기의 줄임말. 주로 휴대폰 배경화면이나 앱 아이콘을 커스텀 하는 것을 뜻함.","retrieved":1677442817624},{"title":"뽀시래기","contents":"부스러기처럼 작고 귀엽다는 뜻의 MZ세대식 표현.","retrieved":1677442817626}]}