{"title":"Careet ─ Contents ─ MZ 용어 사전","url":"https://www.careet.net/Dictionary","favicon":"https://www.careet.net/content/images/favicon.ico","elements":[{"title":"랜봉","contents":"판매하는 아이템을 랜덤하게 봉투에 담았다는 뜻.","retrieved":1689398325992},{"title":"버블","contents":"스타와 마치 1:1 메시지를 주고받는 것처럼 소통할 수 있게 만들어진 프라이빗 메시지 앱. 유료로 이용이 가능하며 아이돌 팬덤이 활발하게 이용하는 서비스로 유명함.","retrieved":1689398325993},{"title":"국룰","contents":"국민 룰의 줄임말. 보편적으로 통용되는 규칙 혹은 유행이라는 뜻.","retrieved":1689398325994},{"title":"초멘","contents":"안면이 없다는 뜻의 ‘초면’과 ‘멘션을 합친 트위터 용어.","retrieved":1689398325995},{"title":"키자니아","contents":"어린이들이 직업을 체험할 수 있는 테마파크. 특정 직업을 생생하게 표현하거나 보여주는 콘텐츠를 볼 때 ‘어른들의 키자니아’라는 댓글이 많이 달림.","retrieved":1689398325996},{"title":"빙의글","contents":"좋아하는 연예인을 대상으로 특정 상황을 설정해 작성한 글.","retrieved":1689398326003}]}