{"title":"Careet ─ Contents ─ MZ 용어 사전","url":"https://www.careet.net/Dictionary","favicon":"https://www.careet.net/content/images/favicon.ico","elements":[{"contents":"~에 대해 집착이 있는 사람을 뜻하는 MZ세대의 신조어.","retrieved":1713414014590},{"contents":"접촉하다라는 뜻의 '콘택트(contact)'와 부정어 '언(un-)'을 합성한 말.  비대면 방식을 뜻함.","retrieved":1713414014591},{"contents":"‘Outfit Of The Day’의 줄임말. 당일 또는 특정 상황에서 입은 자신의 옷차림을 촬영하여 소셜미디어에 업로드하는 행위.","retrieved":1713414014592},{"contents":"‘닥치고 눈팅 삼년’의 줄임말. 주로 커뮤니티 유저들 사이에서 사용되는 용어로, 처음 커뮤니티 활동을 시작할 때 규칙이나 분위기를 충분히 파악하고 활동하라는 뜻.","retrieved":1713414014594},{"contents":"‘그냥 생’의 준말. 갓생에 반대되는 말로 부지런하고 알찬 삶을 살지 말고 그냥 있는대로 살자는 뜻.","retrieved":1713414014595},{"contents":"척척 박사를 변형한 신조어. 먹는 것에 진심인 사람들을 일컬음.","retrieved":1713414014596}]}