{"title":"Careet ─ Contents ─ MZ 용어 사전","url":"https://www.careet.net/Dictionary","favicon":"https://www.careet.net/content/images/favicon.ico","elements":[{"title":"DM","contents":"다이렉트 메시지(Direct Message)의 줄임말.","retrieved":1674178634769},{"title":"에듀테이너","contents":"교육 분야에서 활동하는 연예인 또는 엔터테이너. 에듀케이션(Education)과 엔터테이너(Entertainer)의 합성어.","retrieved":1674178634772},{"title":"관종","contents":"'관심 종자'의 줄임말. 유난히 튀는 행동이나 말을 많이 하는 사람을 뜻함.","retrieved":1674178634775},{"title":"모바일 네이티브","contents":"어릴 적부터 모바일 기기를 접하고 자유자재로 구사하는 세대. 1990년대 중반 이후 출생자.","retrieved":1674178634776},{"title":"근자감","contents":"근거 없는 자신감의 줄임말.","retrieved":1674178634778},{"title":"차도남","contents":"차가운 도시 남자의 줄임말.","retrieved":1674178634784}]}