{"title":"Careet ─ Contents ─ MZ 용어 사전","url":"https://www.careet.net/Dictionary","favicon":"https://www.careet.net/content/images/favicon.ico","elements":[{"contents":"‘갑자기 툭 튀어나오다’의 줄임말","retrieved":1711289682416},{"contents":"칼선이 들어가 모양대로 뗄 수 있는 스티커. 일반적으로 한 장에 스티커 하나씩 들어가 있는 형태가 많음.","retrieved":1711289682417},{"contents":"덕후+力(힘)의 합성어로, 팬심이 깊은 사람에게 덕력이 높다는 표현을 씀.","retrieved":1711289682419},{"contents":"스마트폰에서 사용하는 그림 형태의 문자.","retrieved":1711289682419},{"contents":"코로나 시국의 줄임말.","retrieved":1711289682423},{"contents":"창작물을 공유할 수 있는 블로그 플랫폼.","retrieved":1711289682423}]}