{"title":"Careet ─ Contents ─ MZ 용어 사전","url":"https://www.careet.net/Dictionary","favicon":"https://www.careet.net/content/images/favicon.ico","elements":[{"title":"앨범깡","contents":"앨범 언박싱을 부르는 말. 주로 원하는 포토카드를 얻기 위해 연속해서 앨범을 열어보는 것을 말함.","retrieved":1652394319184},{"title":"미공포","contents":"‘미공개 포토카드’의 줄임말. 앨범에 수록된 ‘공식 포토카드’를 제외한 포토카드를 일컬음. 보통 아이돌 팬들이 각종 이벤트에 참여해서 받게 되는 경우가 많음.","retrieved":1652394319185},{"title":"공병템","contents":"공병이 될 때까지 싹싹 긁어 쓸 정도로 잘 맞는 아이템이라는 뜻. 뷰티 카테고리에서 주로 쓰이는 표현.","retrieved":1652394319185},{"title":"키자니아","contents":"어린이들이 직업을 체험할 수 있는 테마파크. 특정 직업을 생생하게 표현하거나 보여주는 콘텐츠를 볼 때 ‘어른들의 키자니아’라는 댓글이 많이 달림.","retrieved":1652394319186},{"title":"블친","contents":"블로그 친구의 줄임말.","retrieved":1652394319187},{"title":"영통팬싸","contents":"영상 통화로 하는 팬 사인회의 줄임말. 코로나 사태 이후 활성화 된 비대면 팬 이벤트 종류의 하나.","retrieved":1652394319188}]}