{"title":"Careet ─ Contents ─ MZ 용어 사전","url":"https://www.careet.net/Dictionary","favicon":"https://www.careet.net/content/images/favicon.ico","elements":[{"title":"실트","contents":"트위터 ‘실시간 트렌드’라는 뜻. 현재 얘기가 많이 이루어지는 주제를 트위터 프로그램이 인지해 실시간 트렌드로 올리기 때문에 지금 무엇이 화제인지 알 수 있음.","retrieved":1669005051366},{"title":"손민수","contents":"웹툰 &lt;치즈인더트랩&gt;의 등장인물로 주인공 홍설을 몰래 따라하는 캐릭터. MZ세대 사이에서 ‘따라한다’ = ‘손민수 한다’로 통함.","retrieved":1669005051367},{"title":"좋댓구알","contents":"좋아요, 댓글, 구독, 알림설정의 줄임말","retrieved":1669005051367},{"title":"킬포","contents":"‘킬링 포인트’의 줄임말. ‘하이라이트’와 비슷한 의미로 사용됨.","retrieved":1669005051368},{"title":"오픈런","contents":"특정 상품을 구하기 위해 매장 오픈 시간 전에 줄을 서서 대기하는 행위. 공연계에서 쓰는 ‘오픈런’과는 다른 뜻.","retrieved":1669005051370},{"title":"쩝쩝 박사","contents":"척척 박사를 변형한 신조어. 먹는 것에 진심인 사람들을 일컬음.","retrieved":1669005051371}]}