{"title":"Careet ─ Contents ─ MZ 용어 사전","url":"https://www.careet.net/Dictionary","favicon":"https://www.careet.net/content/images/favicon.ico","elements":[{"contents":"특정 분야에 막대한 시간과 정성을 투자하여 경지에 이른 사람을 뜻함. ‘고수’, ‘헤비 유저’와 비슷한 의미.","retrieved":1726597691706},{"contents":"2000년대를 연상시키는 아날로그 감성의 촬영법. 주로 캠코더로 촬영한 듯한 저화질의 영상을 가리킴.","retrieved":1726597691711},{"contents":"엄청나게 버티다라는 뜻.","retrieved":1726597691711},{"contents":"‘소소하지만 확실한 성취감’의 줄임말.","retrieved":1726597691712},{"contents":"상대의 관심을 끌거나 도발하기 위해 자극적인 행동을 하는 것을 뜻하는 인터넷 용어.","retrieved":1726597691712},{"contents":"특정 상품을 구하기 위해 매장 오픈 시간 전에 줄을 서서 대기하는 행위. 공연계에서 쓰는 ‘오픈런’과는 다른 뜻.","retrieved":1726597691713}]}