{"title":"Careet ─ Contents ─ MZ 용어 사전","url":"https://www.careet.net/Dictionary","favicon":"https://www.careet.net/content/images/favicon.ico","elements":[{"title":"총공","contents":"'총 공격'의 줄임말. 팬들의 단체 행동.","retrieved":1654590508930},{"title":"빛삭","contents":"‘빛의 속도로 삭제한다’의 줄임말로 인터넷상에 올린 게시물을 매우 빠르게 지운다는 의미.","retrieved":1654590508931},{"title":"준등기깡","contents":"준등기로 배송된 우편물을 뜯어보는 것. 10~20대는 포토 카드 등 소형 굿즈를 준등기로 거래하는 경우가 많아 생긴 신조어.","retrieved":1654590508933},{"title":"갓생","contents":"god(신)과 인생이 합쳐진 단어로, 부지런하고 알찬 삶을 사는 것을 일컫는 말.","retrieved":1654590508935},{"title":"엄빠","contents":"엄마 아빠를 함께 일컫는 말.","retrieved":1654590508936},{"title":"짠메랑","contents":"‘부메랑(gif 형식으로 사진을 찍어주는 필터)’기능을 활용해 술자리에서 건배하는 모습을 촬영하는 것.","retrieved":1654590508937}]}