{"title":"Careet ─ Contents ─ MZ 용어 사전","url":"https://www.careet.net/Dictionary","favicon":"https://www.careet.net/content/images/favicon.ico","elements":[{"contents":"집에서 하는 요리.","retrieved":1718774349704},{"contents":"‘웃음 참기’의 줄임말. 웃기지만 웃어서 안되는 일이 있을 때 ‘웃음 참기 챌린지’를 한다고 표현하기도 함.","retrieved":1718774349706},{"contents":"움직이는 짤방의 준말. gif 파일로 제작된 이미지를 뜻함.","retrieved":1718774349707},{"contents":"‘미공개 포토카드’의 줄임말. 앨범에 수록된 ‘공식 포토카드’를 제외한 포토카드를 일컬음. 보통 아이돌 팬들이 각종 이벤트에 참여해서 받게 되는 경우가 많음.","retrieved":1718774349708},{"contents":"자신이 직접 그리거나 만든 캐릭터","retrieved":1718774349709},{"contents":"웹툰 &lt;치즈인더트랩&gt;의 등장인물로 주인공 홍설을 몰래 따라하는 캐릭터. MZ세대 사이에서 ‘따라한다’ = ‘손민수 한다’로 통함.","retrieved":1718774349710}]}