{"title":"Careet ─ Contents ─ MZ 용어 사전","url":"https://www.careet.net/Dictionary","favicon":"https://www.careet.net/content/images/favicon.ico","elements":[{"title":"탭꾸","contents":"태블릿 pc 화면 꾸미기","retrieved":1693206987202},{"title":"가심비","contents":"가격 대비 심리적 만족을 추구하는 소비 트렌드↔가성비","retrieved":1693206987204},{"title":"퍼컬","contents":"‘퍼스널 컬러’의 줄임말. 퍼스널 컬러란, 개인의 피부톤에 어울리는 컬러를 뜻하는 말로 요즘 MZ세대는 자신의 퍼스널 컬러에 맞춰 의상, 화장품 등을 구입하려고 함.","retrieved":1693206987206},{"title":"어덕행덕","contents":"‘어차피 덕질할 거 행복하게 덕질하자.’를 줄여 이르는 말.","retrieved":1693206987208},{"title":"컨셉러","contents":"‘콘셉트(concept)’와 ‘~하는 사람(-er)’의 합성어로, 자신만의 설정을 만들어 행동하는 사람을 일컫는 말.","retrieved":1693206987210},{"title":"상플","contents":"‘상상 플레이’의 줄임말. MZ세대가 썰을 풀고 노는 문화를 칭하는 말.","retrieved":1693206987211}]}