{"title":"Careet ─ Contents ─ MZ 용어 사전","url":"https://www.careet.net/Dictionary","favicon":"https://www.careet.net/content/images/favicon.ico","elements":[{"title":"밀레니얼","contents":"1981년~1996년에 출생한 세대를 가리키는 말. 대학내일20대연구소에선 심리적, 사회적 동질성을 고려해 1989년 이전 출생자는 전기 밀레니얼, 1989년 출생자부터는 후기 밀레니얼로 구분하고 있음.","retrieved":1647571633006},{"title":"금손","contents":"손재주가 좋은 사람을 일컫는 말. 반대말은 똥손.","retrieved":1647571633008},{"title":"갑분싸","contents":"‘갑자기 분위기 싸해짐’의 줄임말.","retrieved":1647571633009},{"title":"포토 카드","contents":"아이돌 멤버의 사진으로 만든 카드로, 주로 앨범 당 한 장씩 들어있는 굿즈. 줄여서 ‘포카’라고 부름.","retrieved":1647571633010},{"title":"브이앱","contents":"네이버가 제공하는 연예인 라이브 방송 서비스.","retrieved":1647571633011},{"title":"끌올","contents":"이전에 있었던 일을 다시 끌어 올려 화제로 삼는 일을 부르는 말.","retrieved":1647571633012}]}