{"title":"Careet ─ Contents ─ MZ 용어 사전","url":"https://www.careet.net/Dictionary","favicon":"https://www.careet.net/content/images/favicon.ico","elements":[{"title":"상플","contents":"‘상상 플레이’의 줄임말. MZ세대가 썰을 풀고 노는 문화를 칭하는 말.","retrieved":1648628800401},{"title":"도아너","contents":"도안을 그리는 사람","retrieved":1648628800402},{"title":"사바사","contents":"‘사람 by 사람’의 줄임말. 사람마다 다 다르다는 것을 의미함.","retrieved":1648628800403},{"title":"ㅈㅂㅈㅇ","contents":"정보좀요의 초성을 따서 만든 MZ세대 신조어. 패션 앱 스타일쉐어에서 상대방에게 제품 정보를 물어볼 때 사용했던 것에서 유래함.","retrieved":1648628800404},{"title":"쿠키","contents":"네이버 웹툰에서 유료 결제를 할 수 있는 화폐. ‘유료 결제 한다’라는 뜻으로 ‘쿠키 굽는다’라는 표현을 씀.","retrieved":1648628800405},{"title":"처돌이","contents":"치킨 브랜드 ‘처갓집’의 마스코트 ‘처돌이’에서 유래한 말. 특정 대상을 매우 좋아한다는 뜻.","retrieved":1648628800406}]}