{"title":"Careet ─ Contents ─ MZ 용어 사전","url":"https://www.careet.net/Dictionary","favicon":"https://www.careet.net/content/images/favicon.ico","elements":[{"title":"인용 알티","contents":"트위터에서 다른 사람의 트윗 위에 자신의 의견을 덧붙여서 공유하는 기능.","retrieved":1679048471587},{"title":"학예사","contents":"박물관, 미술관 등에서 작품 등을 수집, 전시 기획 등을 하는 전문 직업.","retrieved":1679048471590},{"title":"세포마켓","contents":"1인 미디어 시대에서 SNS를 통해 이뤄지는 1인 마켓. 기업 단위가 아닌 1인 사업자가 주를 이뤄 세포가 분열하는 것처럼 개인 단위로 발전하는 현상을 뜻함.","retrieved":1679048471596},{"title":"망붕","contents":"‘망상 분자’를 ‘망상 붕자’로 발음을 뭉갠 것의 줄임말. 사실이 아니지만 믿고 싶어 하는 것을 의미함.","retrieved":1679048471597},{"title":"블챌","contents":"‘블로그 챌린지’의 줄임말. 6월부터 12월까지 6개월간 진행되는 장기 프로젝트로 매주 지정된 카테고리에 한 건 이상의 일기를 작성해야 챌린지를 이어갈 수 있음.","retrieved":1679048471598},{"title":"GOAT","contents":"‘Greatest Of All Time’의 줄임말. 최근 MZ세대 사이에서 역대급 레전드를 논할 때 자주 쓰이는 표현.","retrieved":1679048471600}]}